{
  "paperId": "4f75648de8d035f588f4e69effdc8e01466ae9cb",
  "externalIds": {
    "MAG": "175693411",
    "CorpusId": 92458633
  },
  "url": "https://www.semanticscholar.org/paper/4f75648de8d035f588f4e69effdc8e01466ae9cb",
  "title": "Amitraz Exposure and Risks to Pesticide Applicators and Nearby Residents in Zangiabad, Iran",
  "venue": "",
  "year": 2010,
  "citationCount": 1,
  "influentialCitationCount": 0,
  "openAccessPdf": {
    "url": "",
    "status": null,
    "license": null
  },
  "fieldsOfStudy": [
    "Chemistry"
  ],
  "publicationTypes": [
    "Review"
  ],
  "authors": [
    {
      "authorId": "122770984",
      "name": "M. aghasi"
    }
  ],
  "abstract": null,
  "references": null
}